lime_trader/__init__.py
lime_trader/api/__init__.py
lime_trader/api/api_client.py
lime_trader/api/authenticated_api_client.py
lime_trader/async_trader/__init__.py
lime_trader/async_trader/api/__init__.py
lime_trader/async_trader/api/async_api_client.py
lime_trader/async_trader/api/async_authenticated_api_client.py
lime_trader/async_trader/async_client.py
lime_trader/async_trader/clients/__init__.py
lime_trader/async_trader/clients/async_account_client.py
lime_trader/async_trader/clients/async_market_data_client.py
lime_trader/async_trader/clients/async_trading_client.py
lime_trader/client.py
lime_trader/clients/__init__.py
lime_trader/clients/account_client.py
lime_trader/clients/account_feed_client.py
lime_trader/clients/market_data_client.py
lime_trader/clients/trading_client.py
lime_trader/constants/__init__.py
lime_trader/constants/config.py
lime_trader/constants/urls.py
lime_trader/converters/__init__.py
lime_trader/converters/abstract_converter.py
lime_trader/converters/cattr_converter.py
lime_trader/exceptions/__init__.py
lime_trader/exceptions/api_error.py
lime_trader/handlers/__init__.py
lime_trader/handlers/account_feed_handler.py
lime_trader/models/__init__.py
lime_trader/models/accounts.py
lime_trader/models/errors.py
lime_trader/models/market.py
lime_trader/models/page.py
lime_trader/models/token_storage.py
lime_trader/models/trading.py
lime_trader/utils/__init__.py
lime_trader/utils/date_utils.py
lime_trader/utils/http_event_handlers.py
lime_trader/utils/logging_utils.py
lime_trader/utils/pagination.py
lime_trader_sdk-0.3.12.dist-info/METADATA
lime_trader_sdk-0.3.12.dist-info/WHEEL
lime_trader_sdk-0.3.12.dist-info/RECORD
