Metadata-Version: 2.1
Name: lime-trader-sdk
Version: 0.3.12
Summary: Python wrapper for Lime Trader REST API (https://docs.lime.co/trader/)
Author: Lime Financial
Author-email: support@lime.co
Requires-Python: >=3.10,<4.0
Classifier: Programming Language :: Python :: 3
Classifier: Programming Language :: Python :: 3.10
Classifier: Programming Language :: Python :: 3.11
Classifier: Programming Language :: Python :: 3.12
Classifier: Programming Language :: Python :: 3.13
Requires-Dist: attrs (>=22.2.0,<23.0.0)
Requires-Dist: cattrs (>=22.2.0,<23.0.0)
Requires-Dist: httpx (>=0.25.1,<0.26.0)
Requires-Dist: orjson (>=3.9.10,<4.0.0)
Requires-Dist: python-dotenv (>=1.0.0,<2.0.0)
Requires-Dist: rel (>=0.4.8,<0.5.0)
Requires-Dist: requests (>=2.30.0,<3.0.0)
Requires-Dist: websocket-client (>=1.6.4,<2.0.0)
